adafruit_ble_magic_light.py
adafruit_circuitpython_ble_magic_light-0.9.25.dist-info/licenses/LICENSE
adafruit_circuitpython_ble_magic_light-0.9.25.dist-info/METADATA
adafruit_circuitpython_ble_magic_light-0.9.25.dist-info/WHEEL
adafruit_circuitpython_ble_magic_light-0.9.25.dist-info/top_level.txt
adafruit_circuitpython_ble_magic_light-0.9.25.dist-info/RECORD
